tradera_api/__init__.py
tradera_api/tradera.py
tradera_api-0.0.1.dist-info/LICENSE
tradera_api-0.0.1.dist-info/METADATA
tradera_api-0.0.1.dist-info/WHEEL
tradera_api-0.0.1.dist-info/RECORD
