Metadata-Version: 2.1
Name: tradera_api
Version: 0.0.1
Summary: A python API wrapper for tradera.se
Author: dunderrrrrr
Author-email: emil.bjorkroth@gmail.com
Requires-Python: >=3.10,<4.0
Classifier: Programming Language :: Python :: 3
Classifier: Programming Language :: Python :: 3.10
Classifier: Programming Language :: Python :: 3.11
Classifier: Programming Language :: Python :: 3.12
Requires-Dist: httpx (>=0.27.0,<0.28.0)
Requires-Dist: mypy (>=1.15.0,<2.0.0)
Requires-Dist: pre-commit (>=3.7.1,<4.0.0)
Requires-Dist: ruff (>=0.5.2,<0.6.0)
